argsense/__init__.py
argsense/__main__.py
argsense/api.py
argsense/cli.py
argsense/config.py
argsense/converter.py
argsense/parser/__init__.py
argsense/parser/args_parser/__init__.py
argsense/parser/args_parser/argv.py
argsense/parser/args_parser/exceptions.py
argsense/parser/args_parser/params.py
argsense/parser/args_parser/parser.py
argsense/parser/docs_parser.py
argsense/parser/func_parser.py
argsense/renderer/__init__.py
argsense/renderer/psg/__init__.py
argsense/renderer/psg/launcher.png
argsense/renderer/psg/main.py
argsense/renderer/rich/__init__.py
argsense/renderer/rich/artist.py
argsense/renderer/rich/render.py
argsense/renderer/rich/style/__init__.py
argsense/renderer/rich/style/palette.py
argsense/renderer/textual/__init__.py
argsense/renderer/textual/_broken.py
argsense/renderer/textual/app.py
argsense/renderer/textual/bottom_bar.py
argsense/renderer/textual/main_desc.py
argsense/renderer/textual/main_form.py
argsense/renderer/textual/sidebar.py
argsense/renderer/textual/textual_sugar/__init__.py
argsense/renderer/textual/textual_sugar/binding.py
argsense/renderer/textual/textual_sugar/chore.py
argsense/renderer/textual/textual_sugar/logger.py
argsense/renderer/textual/textual_sugar/signal.py
argsense/renderer/textual/textual_sugar/widgets.py
argsense/renderer/textual/tooltip.py
argsense/renderer/textual/typehint.py
argsense-1.1.0.dist-info/entry_points.txt
argsense-1.1.0.dist-info/LICENSE
argsense-1.1.0.dist-info/METADATA
argsense-1.1.0.dist-info/WHEEL
argsense-1.1.0.dist-info/RECORD
