Metadata-Version: 2.3
Name: argsense
Version: 1.1.0
Summary: New command line interface based on Rich library.
License: MIT
Author: Likianta
Author-email: likianta@foxmail.com
Requires-Python: >=3.8
Classifier: License :: OSI Approved :: MIT License
Classifier: Programming Language :: Python :: 3
Classifier: Programming Language :: Python :: 3.8
Classifier: Programming Language :: Python :: 3.9
Classifier: Programming Language :: Python :: 3.10
Classifier: Programming Language :: Python :: 3.11
Classifier: Programming Language :: Python :: 3.12
Classifier: Programming Language :: Python :: 3.13
Provides-Extra: gui
Requires-Dist: lk-logger (>=6.0.6,<7.0.0)
Requires-Dist: pysimplegui ; extra == "gui"
Requires-Dist: rich (>=13.9.0)
Project-URL: Homepage, https://github.com/likianta/argsense-cli
